pspm/__init__.py
pspm/__main__.py
pspm/cli.py
pspm/entities/__init__.py
pspm/entities/command_runner.py
pspm/entities/installer.py
pspm/entities/package_manager.py
pspm/entities/pyproject.py
pspm/entities/resolver.py
pspm/entities/toml.py
pspm/entities/venv_runner.py
pspm/entities/virtual_env.py
pspm/errors/__init__.py
pspm/errors/command.py
pspm/errors/dependencies.py
pspm/services/__init__.py
pspm/services/bootstrap.py
pspm/services/dependencies.py
pspm/services/run.py
pspm/utils/__init__.py
pspm/utils/bin_path.py
pspm/utils/commands.py
pspm/utils/printing.py
pspm-1.10.0.dist-info/METADATA
pspm-1.10.0.dist-info/WHEEL
pspm-1.10.0.dist-info/entry_points.txt
pspm-1.10.0.dist-info/licenses/LICENSE
pspm-1.10.0.dist-info/RECORD
