Metadata-Version: 2.4
Name: pspm
Version: 1.10.0
Summary: A simple Python package manager
Project-URL: Repository, https://codeberg.org/Jahn16/pspm
Project-URL: Documentation, https://pspm.jahn16.com
Project-URL: Releases, https://codeberg.org/Jahn16/pspm/releases
Author-email: Jahn16 <jpdeoliveiraferreira@gmail.com>
License:                     GNU GENERAL PUBLIC LICENSE
License-File: LICENSE
Keywords: dependency,packaging,workflow
Classifier: Programming Language :: Python
Classifier: Topic :: Software Development :: Build Tools
Requires-Python: >=3.9
Requires-Dist: copier
Requires-Dist: tomli-w
Requires-Dist: tomli; python_version < '3.11'
Requires-Dist: typer
Provides-Extra: docs
Requires-Dist: markdown-gfm-admonition; extra == 'docs'
Requires-Dist: mkdocs; extra == 'docs'
Requires-Dist: mkdocs-awesome-pages-plugin; extra == 'docs'
Requires-Dist: mkdocs-material; extra == 'docs'
Provides-Extra: test
Requires-Dist: pytest; extra == 'test'
Requires-Dist: uv>=0.4.8; extra == 'test'
Provides-Extra: uv
Requires-Dist: uv>=0.4.8; extra == 'uv'
